nd123/mymodule.py
nd123-0.2.dist-info/METADATA
nd123-0.2.dist-info/WHEEL
nd123-0.2.dist-info/top_level.txt
nd123-0.2.dist-info/RECORD
