Metadata-Version: 2.1
Name: nd123
Version: 0.2
Summary: nerul test
Home-page: UNKNOWN
Author: Pinnacle
Author-email: kamalsir@ymail.com
License: UNKNOWN
Platform: UNKNOWN
